[
    {
        "line_number": 1,
        "text": "शिवविवाह । ",
        "image_path": "datasetProcessed/cropped_textlines/images/hajarilala1919_15_textline_1.png",
        "bounding_box": {
            "x1": 574,
            "y1": 199,
            "x2": 1125,
            "y2": 366
        }
    },
    {
        "line_number": 2,
        "text": "देवन जेंवत जानी पुरकी सुन्दरि स्यानी,",
        "image_path": "datasetProcessed/cropped_textlines/images/hajarilala1919_15_textline_2.png",
        "bounding_box": {
            "x1": 31,
            "y1": 362,
            "x2": 1693,
            "y2": 531
        }
    },
    {
        "line_number": 3,
        "text": "मधुर सरस बानी हिये प्रेमभावहीं । गा-",
        "image_path": "datasetProcessed/cropped_textlines/images/hajarilala1919_15_textline_3.png",
        "bounding_box": {
            "x1": 26,
            "y1": 527,
            "x2": 1676,
            "y2": 675
        }
    },
    {
        "line_number": 4,
        "text": "वति मंगलगारी सुरन को नामधारी, ब्यंग",
        "image_path": "datasetProcessed/cropped_textlines/images/hajarilala1919_15_textline_4.png",
        "bounding_box": {
            "x1": 21,
            "y1": 676,
            "x2": 1671,
            "y2": 823
        }
    },
    {
        "line_number": 5,
        "text": "बैन मुदकारी बहुत सुनावहीं ।। सुनि",
        "image_path": "datasetProcessed/cropped_textlines/images/hajarilala1919_15_textline_5.png",
        "bounding_box": {
            "x1": 23,
            "y1": 827,
            "x2": 1695,
            "y2": 969
        }
    },
    {
        "line_number": 6,
        "text": "सुनि देवगन हँसत मुदित मन, प्रेमपुल-",
        "image_path": "datasetProcessed/cropped_textlines/images/hajarilala1919_15_textline_6.png",
        "bounding_box": {
            "x1": 23,
            "y1": 965,
            "x2": 1713,
            "y2": 1119
        }
    },
    {
        "line_number": 7,
        "text": "कित तन बर सुख पावहीं । अधिक बिलम्ब",
        "image_path": "datasetProcessed/cropped_textlines/images/hajarilala1919_15_textline_7.png",
        "bounding_box": {
            "x1": 18,
            "y1": 1126,
            "x2": 1673,
            "y2": 1263
        }
    },
    {
        "line_number": 8,
        "text": "लाइ जेंवें सब हरषाइ, सुखसो न कहिजाइ",
        "image_path": "datasetProcessed/cropped_textlines/images/hajarilala1919_15_textline_8.png",
        "bounding_box": {
            "x1": 11,
            "y1": 1264,
            "x2": 1669,
            "y2": 1419
        }
    },
    {
        "line_number": 9,
        "text": "कैसेको बतावहीं २७ जेंई सुर समुदाइ",
        "image_path": "datasetProcessed/cropped_textlines/images/hajarilala1919_15_textline_9.png",
        "bounding_box": {
            "x1": 4,
            "y1": 1405,
            "x2": 1656,
            "y2": 1580
        }
    },
    {
        "line_number": 10,
        "text": "हृदये आनन्दछाइ, अँचई गै पान पाइ",
        "image_path": "datasetProcessed/cropped_textlines/images/hajarilala1919_15_textline_10.png",
        "bounding_box": {
            "x1": 9,
            "y1": 1559,
            "x2": 1654,
            "y2": 1716
        }
    },
    {
        "line_number": 11,
        "text": "निज निज बासहीं । आये पुनि मुनिजन",
        "image_path": "datasetProcessed/cropped_textlines/images/hajarilala1919_15_textline_11.png",
        "bounding_box": {
            "x1": 1,
            "y1": 1693,
            "x2": 1673,
            "y2": 1864
        }
    },
    {
        "line_number": 12,
        "text": "मुदित अधिकमन, गुणिब्याह लगनजो",
        "image_path": "datasetProcessed/cropped_textlines/images/hajarilala1919_15_textline_12.png",
        "bounding_box": {
            "x1": 0,
            "y1": 1851,
            "x2": 1701,
            "y2": 2000
        }
    },
    {
        "line_number": 13,
        "text": "हिमगिरि पासहीं ।। सुनि शुभलग्न बर",
        "image_path": "datasetProcessed/cropped_textlines/images/hajarilala1919_15_textline_13.png",
        "bounding_box": {
            "x1": 0,
            "y1": 2001,
            "x2": 1649,
            "y2": 2147
        }
    },
    {
        "line_number": 14,
        "text": "मुदित गिरीश उर, पठये बुलाइ सुर सब",
        "image_path": "datasetProcessed/cropped_textlines/images/hajarilala1919_15_textline_14.png",
        "bounding_box": {
            "x1": 4,
            "y1": 2143,
            "x2": 1654,
            "y2": 2301
        }
    },
    {
        "line_number": 15,
        "text": "जनवासहीं । सुनतहिं ततक्षण आये सब",
        "image_path": "datasetProcessed/cropped_textlines/images/hajarilala1919_15_textline_15.png",
        "bounding_box": {
            "x1": 0,
            "y1": 2298,
            "x2": 1654,
            "y2": 2442
        }
    },
    {
        "line_number": 16,
        "text": "देवगण, पाइ बर आसनन बैठे सुहुला-",
        "image_path": "datasetProcessed/cropped_textlines/images/hajarilala1919_15_textline_16.png",
        "bounding_box": {
            "x1": 4,
            "y1": 2437,
            "x2": 1661,
            "y2": 2588
        }
    },
    {
        "line_number": 17,
        "text": "१५",
        "image_path": "datasetProcessed/cropped_textlines/images/hajarilala1919_15_textline_17.png",
        "bounding_box": {
            "x1": 1492,
            "y1": 228,
            "x2": 1664,
            "y2": 372
        }
    }
]