[
    {
        "line_number": 1,
        "text": "कथाप्रारंभ ॥",
        "image_path": "datasetProcessed/cropped_textlines/images/nivajakavi1895_01_textline_1.png",
        "bounding_box": {
            "x1": 978,
            "y1": 1170,
            "x2": 1743,
            "y2": 1380
        }
    },
    {
        "line_number": 2,
        "text": "श्रीगणेशाय नमः",
        "image_path": "datasetProcessed/cropped_textlines/images/nivajakavi1895_01_textline_2.png",
        "bounding_box": {
            "x1": 1068,
            "y1": 1033,
            "x2": 1599,
            "y2": 1149
        }
    },
    {
        "line_number": 3,
        "text": "काब्य बद्ध",
        "image_path": "datasetProcessed/cropped_textlines/images/nivajakavi1895_01_textline_3.png",
        "bounding_box": {
            "x1": 1041,
            "y1": 1443,
            "x2": 1587,
            "y2": 1648
        }
    },
    {
        "line_number": 4,
        "text": "कीन्हों । देह को दीन्होंकलेश महा मिटि भेष गयोन",
        "image_path": "datasetProcessed/cropped_textlines/images/nivajakavi1895_01_textline_4.png",
        "bounding_box": {
            "x1": 217,
            "y1": 2247,
            "x2": 2423,
            "y2": 2416
        }
    },
    {
        "line_number": 5,
        "text": "सन यों इन्द्रासन इन्द्र को चाहत लीन्हों ८ अन्हैबे",
        "image_path": "datasetProcessed/cropped_textlines/images/nivajakavi1895_01_textline_5.png",
        "bounding_box": {
            "x1": 213,
            "y1": 2699,
            "x2": 2411,
            "y2": 2854
        }
    },
    {
        "line_number": 6,
        "text": "शकुन्तला दुष्यन्त के गन्धर्व विवाह के विषय में",
        "image_path": "datasetProcessed/cropped_textlines/images/nivajakavi1895_01_textline_6.png",
        "bounding_box": {
            "x1": 207,
            "y1": 1654,
            "x2": 2435,
            "y2": 1872
        }
    },
    {
        "line_number": 7,
        "text": "परै कछु चीन्हों ॥ निशिबासर नेमकियो ही निवाज,",
        "image_path": "datasetProcessed/cropped_textlines/images/nivajakavi1895_01_textline_7.png",
        "bounding_box": {
            "x1": 221,
            "y1": 2395,
            "x2": 2423,
            "y2": 2572
        }
    },
    {
        "line_number": 8,
        "text": "निरंजन के पद मैं चित दीन्हों । साधिकै योग को आ-",
        "image_path": "datasetProcessed/cropped_textlines/images/nivajakavi1895_01_textline_8.png",
        "bounding_box": {
            "x1": 180,
            "y1": 2551,
            "x2": 2444,
            "y2": 2722
        }
    },
    {
        "line_number": 9,
        "text": "कूलनि । चारिहू आगि के बीच में बैठि सह्यो सविता",
        "image_path": "datasetProcessed/cropped_textlines/images/nivajakavi1895_01_textline_9.png",
        "bounding_box": {
            "x1": 221,
            "y1": 3000,
            "x2": 2427,
            "y2": 3165
        }
    },
    {
        "line_number": 10,
        "text": "सन्ताप के शूलनि ॥ धूम को पान अमान कियो पग",
        "image_path": "datasetProcessed/cropped_textlines/images/nivajakavi1895_01_textline_10.png",
        "bounding_box": {
            "x1": 189,
            "y1": 3156,
            "x2": 2415,
            "y2": 3316
        }
    },
    {
        "line_number": 11,
        "text": "ऊरध बांधि अधोमुख झूलनि । चौंसठि साल विशाल",
        "image_path": "datasetProcessed/cropped_textlines/images/nivajakavi1895_01_textline_11.png",
        "bounding_box": {
            "x1": 213,
            "y1": 3300,
            "x2": 2408,
            "y2": 3463
        }
    },
    {
        "line_number": 12,
        "text": "ऋषीश्वर खाइ रह्यो बन के फल फूलनि ९ ॥",
        "image_path": "datasetProcessed/cropped_textlines/images/nivajakavi1895_01_textline_12.png",
        "bounding_box": {
            "x1": 225,
            "y1": 3460,
            "x2": 2095,
            "y2": 3616
        }
    },
    {
        "line_number": 13,
        "text": "एक समय मुनिनायक कौशिक कानन जाय महातप",
        "image_path": "datasetProcessed/cropped_textlines/images/nivajakavi1895_01_textline_13.png",
        "bounding_box": {
            "x1": 361,
            "y1": 2087,
            "x2": 2435,
            "y2": 2269
        }
    },
    {
        "line_number": 14,
        "text": "कों तीरथ कोऊ बचो न फिस्यो सिगरीं सरतानि के",
        "image_path": "datasetProcessed/cropped_textlines/images/nivajakavi1895_01_textline_14.png",
        "bounding_box": {
            "x1": 221,
            "y1": 2844,
            "x2": 2435,
            "y2": 3021
        }
    },
    {
        "line_number": 15,
        "text": "घनाक्षरी छंद",
        "image_path": "datasetProcessed/cropped_textlines/images/nivajakavi1895_01_textline_15.png",
        "bounding_box": {
            "x1": 1045,
            "y1": 3644,
            "x2": 1638,
            "y2": 3814
        }
    },
    {
        "line_number": 16,
        "text": "अरु प्रबल अनल वारि धरि कें । जाड़े के दिननि",
        "image_path": "datasetProcessed/cropped_textlines/images/nivajakavi1895_01_textline_16.png",
        "bounding_box": {
            "x1": 225,
            "y1": 3964,
            "x2": 2461,
            "y2": 4128
        }
    },
    {
        "line_number": 17,
        "text": "धूपके दिननि हेरैमन मुख सूरज सों सन्मुख चाहे",
        "image_path": "datasetProcessed/cropped_textlines/images/nivajakavi1895_01_textline_17.png",
        "bounding_box": {
            "x1": 365,
            "y1": 3804,
            "x2": 2423,
            "y2": 3982
        }
    },
    {
        "line_number": 18,
        "text": "सवैया",
        "image_path": "datasetProcessed/cropped_textlines/images/nivajakavi1895_01_textline_18.png",
        "bounding_box": {
            "x1": 1147,
            "y1": 1939,
            "x2": 1474,
            "y2": 2121
        }
    }
]