[
    {
        "line_number": 1,
        "text": "जात त्यों त्यों हरि दिननि बढ़त जात जोति है । छिन",
        "image_path": "datasetProcessed/cropped_textlines/images/nivajakavi1895_06_textline_1.png",
        "bounding_box": {
            "x1": 475,
            "y1": 382,
            "x2": 2697,
            "y2": 625
        }
    },
    {
        "line_number": 2,
        "text": "और देखिये घरी में कछु और और और छिन छिन",
        "image_path": "datasetProcessed/cropped_textlines/images/nivajakavi1895_06_textline_2.png",
        "bounding_box": {
            "x1": 463,
            "y1": 538,
            "x2": 2697,
            "y2": 774
        }
    },
    {
        "line_number": 3,
        "text": "घरी घरी औरै द्युति होति है २९ ॥",
        "image_path": "datasetProcessed/cropped_textlines/images/nivajakavi1895_06_textline_3.png",
        "bounding_box": {
            "x1": 467,
            "y1": 698,
            "x2": 1962,
            "y2": 900
        }
    },
    {
        "line_number": 4,
        "text": "दोहा । सुन्दर वैसो बर मिले शकुन्तला ज्यों आप ।",
        "image_path": "datasetProcessed/cropped_textlines/images/nivajakavi1895_06_textline_4.png",
        "bounding_box": {
            "x1": 506,
            "y1": 850,
            "x2": 2603,
            "y2": 1074
        }
    },
    {
        "line_number": 5,
        "text": "कीन्हों श्रम इतनो न जाकी कछु माप है । दिन चढ़ि",
        "image_path": "datasetProcessed/cropped_textlines/images/nivajakavi1895_06_textline_5.png",
        "bounding_box": {
            "x1": 443,
            "y1": 1580,
            "x2": 2646,
            "y2": 1819
        }
    },
    {
        "line_number": 6,
        "text": "आयो बढ़ि कढ़ि अति दूरे पैन पायो तोऊ यातें चढ़ि",
        "image_path": "datasetProcessed/cropped_textlines/images/nivajakavi1895_06_textline_6.png",
        "bounding_box": {
            "x1": 434,
            "y1": 1736,
            "x2": 2650,
            "y2": 1972
        }
    },
    {
        "line_number": 7,
        "text": "ने दौड़े बाण सों मिलाय खैंचि कान लगि चाप है ।",
        "image_path": "datasetProcessed/cropped_textlines/images/nivajakavi1895_06_textline_7.png",
        "bounding_box": {
            "x1": 428,
            "y1": 2028,
            "x2": 2646,
            "y2": 2280
        }
    },
    {
        "line_number": 8,
        "text": "सबसैना पीछै हिरिना के आप है ३२ ॥",
        "image_path": "datasetProcessed/cropped_textlines/images/nivajakavi1895_06_textline_8.png",
        "bounding_box": {
            "x1": 432,
            "y1": 2333,
            "x2": 2072,
            "y2": 2559
        }
    },
    {
        "line_number": 9,
        "text": "चि लियो शर सास्यो । चोट करैं जब लों तब लों ऋषि",
        "image_path": "datasetProcessed/cropped_textlines/images/nivajakavi1895_06_textline_9.png",
        "bounding_box": {
            "x1": 404,
            "y1": 2641,
            "x2": 2618,
            "y2": 2866
        }
    },
    {
        "line_number": 10,
        "text": "की करिबे कों भयो अवतार तिहारो । हाहा रह्यो मह-",
        "image_path": "datasetProcessed/cropped_textlines/images/nivajakavi1895_06_textline_10.png",
        "bounding_box": {
            "x1": 412,
            "y1": 2941,
            "x2": 2622,
            "y2": 3173
        }
    },
    {
        "line_number": 11,
        "text": "नहिं नृप बाणचलायो ॥ बागें गहि रथ ठाढ़ों कीन्हो ।",
        "image_path": "datasetProcessed/cropped_textlines/images/nivajakavi1895_06_textline_11.png",
        "bounding_box": {
            "x1": 400,
            "y1": 3386,
            "x2": 2607,
            "y2": 3616
        }
    },
    {
        "line_number": 12,
        "text": "आशिर्बाद ऋषिन तब दीन्हो ॥ करि प्रणाम नृप पूछौ",
        "image_path": "datasetProcessed/cropped_textlines/images/nivajakavi1895_06_textline_12.png",
        "bounding_box": {
            "x1": 404,
            "y1": 3527,
            "x2": 2670,
            "y2": 3768
        }
    },
    {
        "line_number": 13,
        "text": "पुंजनि परि हरें । मुनिवर को चलि दरशन करें ॥ यह",
        "image_path": "datasetProcessed/cropped_textlines/images/nivajakavi1895_06_textline_13.png",
        "bounding_box": {
            "x1": 350,
            "y1": 3839,
            "x2": 2576,
            "y2": 4059
        }
    },
    {
        "line_number": 14,
        "text": "घनाक्षरी । रथ असवार दौरे देखिकें शिकार नृप",
        "image_path": "datasetProcessed/cropped_textlines/images/nivajakavi1895_06_textline_14.png",
        "bounding_box": {
            "x1": 603,
            "y1": 1455,
            "x2": 2669,
            "y2": 1666
        }
    },
    {
        "line_number": 15,
        "text": "करि है ताको ब्याह यह करीप्रतिज्ञा बाप३ ०॥",
        "image_path": "datasetProcessed/cropped_textlines/images/nivajakavi1895_06_textline_15.png",
        "bounding_box": {
            "x1": 807,
            "y1": 1002,
            "x2": 2689,
            "y2": 1224
        }
    },
    {
        "line_number": 16,
        "text": "लागी रहे शकुंतला बन में यह परकार ।",
        "image_path": "datasetProcessed/cropped_textlines/images/nivajakavi1895_06_textline_16.png",
        "bounding_box": {
            "x1": 799,
            "y1": 1158,
            "x2": 2482,
            "y2": 1377
        }
    },
    {
        "line_number": 17,
        "text": "आयो तन तापहै ॥ जाय नजकाने घोड़े पवन के समा-",
        "image_path": "datasetProcessed/cropped_textlines/images/nivajakavi1895_06_textline_17.png",
        "bounding_box": {
            "x1": 443,
            "y1": 1896,
            "x2": 2642,
            "y2": 2109
        }
    },
    {
        "line_number": 18,
        "text": "आगे तें हरिण भाग्यो ताके नृप संग लागो रही पीछे",
        "image_path": "datasetProcessed/cropped_textlines/images/nivajakavi1895_06_textline_18.png",
        "bounding_box": {
            "x1": 432,
            "y1": 2196,
            "x2": 2646,
            "y2": 2425
        }
    },
    {
        "line_number": 19,
        "text": "यह तब । कहो कण्व को आश्रम कहँ अब ॥ आज पाप",
        "image_path": "datasetProcessed/cropped_textlines/images/nivajakavi1895_06_textline_19.png",
        "bounding_box": {
            "x1": 385,
            "y1": 3684,
            "x2": 2603,
            "y2": 3907
        }
    },
    {
        "line_number": 20,
        "text": "सुनि ऋषिन बहुत सुख पायो । आश्रम निपट नगीच",
        "image_path": "datasetProcessed/cropped_textlines/images/nivajakavi1895_06_textline_20.png",
        "bounding_box": {
            "x1": 359,
            "y1": 3983,
            "x2": 2576,
            "y2": 4195
        }
    },
    {
        "line_number": 21,
        "text": "सवैया । फोंक लगाय करेरी कमान में कान लों खैं-",
        "image_path": "datasetProcessed/cropped_textlines/images/nivajakavi1895_06_textline_21.png",
        "bounding_box": {
            "x1": 557,
            "y1": 2497,
            "x2": 2626,
            "y2": 2702
        }
    },
    {
        "line_number": 22,
        "text": "लोगन दूरि तें आनि पुकास्यो ॥ रक्षा ऋषीश्वर लोगन",
        "image_path": "datasetProcessed/cropped_textlines/images/nivajakavi1895_06_textline_22.png",
        "bounding_box": {
            "x1": 424,
            "y1": 2785,
            "x2": 2630,
            "y2": 3007
        }
    },
    {
        "line_number": 23,
        "text": "राज हमारे तजो बन को मृग है मत मारो ३३ ॥",
        "image_path": "datasetProcessed/cropped_textlines/images/nivajakavi1895_06_textline_23.png",
        "bounding_box": {
            "x1": 412,
            "y1": 3097,
            "x2": 2384,
            "y2": 3310
        }
    },
    {
        "line_number": 24,
        "text": "चौपाई । ऋषि लोगन यह टेर सुनायो । मृग पर",
        "image_path": "datasetProcessed/cropped_textlines/images/nivajakavi1895_06_textline_24.png",
        "bounding_box": {
            "x1": 557,
            "y1": 3234,
            "x2": 2607,
            "y2": 3461
        }
    },
    {
        "line_number": 25,
        "text": "एकसमयदुष्यन्तनृप खेलनकढ़योशिकार३१॥",
        "image_path": "datasetProcessed/cropped_textlines/images/nivajakavi1895_06_textline_25.png",
        "bounding_box": {
            "x1": 791,
            "y1": 1314,
            "x2": 2681,
            "y2": 1521
        }
    },
    {
        "line_number": 26,
        "text": "(६)",
        "image_path": "datasetProcessed/cropped_textlines/images/nivajakavi1895_06_textline_26.png",
        "bounding_box": {
            "x1": 1420,
            "y1": 277,
            "x2": 1794,
            "y2": 442
        }
    }
]